[{"__type__":"cc.Prefab","data":{"__id__":1}},{"__type__":"cc.Node","_name":"solider2_blue","_children":[{"__id__":2},{"__id__":25}],"_prefab":{"__type__":"cc.PrefabInfo","root":{"__id__":1},"asset":{"__id__":0},"fileId":"c0mxf9tlJPir9CxR2Y4Jsd","_synced":{"default":false,"serializable":false}}},{"__type__":"cc.Node","_name":"body","_parent":{"__id__":1},"_children":[{"__id__":3}],"_components":[{"__type__":"cc.SkeletalAnimationComponent","_name":"body<SkeletalAnimationComponent>","node":{"__id__":2},"playOnLoad":true,"_clips":[{"__uuid__":"80fxZcrrhHt6l8Q44DX8T4@c2696"},{"__uuid__":"80fxZcrrhHt6l8Q44DX8T4@9292d"},{"__uuid__":"80fxZcrrhHt6l8Q44DX8T4@2cd1c"},{"__uuid__":"80fxZcrrhHt6l8Q44DX8T4@e4391"}],"_defaultClip":{"__uuid__":"80fxZcrrhHt6l8Q44DX8T4@c2696"}}],"_prefab":{"__type__":"cc.PrefabInfo","root":{"__id__":1},"asset":{"__id__":0},"fileId":"dbZj9RV0NN4LLJJ2U8t7RR","_synced":{"default":false,"serializable":false}},"_lrot":{"__type__":"cc.Quat","y":1,"w":6.123233995736766e-17},"_lscale":{"__type__":"cc.Vec3","x":1.4,"y":1.4,"z":1.4},"_euler":{"__type__":"cc.Vec3","y":180}},{"__type__":"cc.Node","_name":"RootNode","_parent":{"__id__":2},"_children":[{"__id__":4}],"_prefab":{"__type__":"cc.PrefabInfo","root":{"__id__":1},"asset":{"__id__":0},"fileId":"4eKBFBVYZDv4K6TS6VmcZL","_synced":{"default":false,"serializable":false}}},{"__type__":"cc.Node","_name":"Ironguard","_parent":{"__id__":3},"_children":[{"__id__":5}],"_prefab":{"__type__":"cc.PrefabInfo","root":{"__id__":1},"asset":{"__id__":0},"fileId":"e7bqqmpxlC0Z2HUNG8yCxr","_synced":{"default":false,"serializable":false}}},{"__type__":"cc.Node","_name":"Ironguard 2","_parent":{"__id__":4},"_children":[{"__id__":6},{"__id__":24}],"_prefab":{"__type__":"cc.PrefabInfo","root":{"__id__":1},"asset":{"__id__":0},"fileId":"2frGq6V+9Mwb8GpzwSimoa","_synced":{"default":false,"serializable":false}},"_lscale":{"__type__":"cc.Vec3","x":256,"y":256,"z":256}},{"__type__":"cc.Node","_name":"Bip001","_parent":{"__id__":5},"_children":[{"__id__":7}],"_prefab":{"__type__":"cc.PrefabInfo","root":{"__id__":1},"asset":{"__id__":0},"fileId":"celjVqTOlJ67T+HwKtCYD0","_synced":{"default":false,"serializable":false}},"_lpos":{"__type__":"cc.Vec3","y":0.000750659091863781,"z":3.48794257365448e-11},"_lrot":{"__type__":"cc.Quat","x":0.5006184104384365,"y":0.5006179932059123,"z":0.49938057094777655,"w":-0.4993814948197932},"_euler":{"__type__":"cc.Vec3","x":-89.99997106669261,"y":-89.99992319610654,"z":0.141769153613246}},{"__type__":"cc.Node","_name":"Bip001 Pelvis","_parent":{"__id__":6},"_children":[{"__id__":8}],"_prefab":{"__type__":"cc.PrefabInfo","root":{"__id__":1},"asset":{"__id__":0},"fileId":"58lpksqRhBu4y91zAFNXWV","_synced":{"default":false,"serializable":false}},"_lrot":{"__type__":"cc.Quat","x":-0.5231530625518911,"y":-0.475720640284164,"z":-0.47572069988880855,"w":0.5231544334587105},"_euler":{"__type__":"cc.Vec3","x":-89.99992106476432,"y":-84.56252939250899,"z":-0.00007830626836422523}},{"__type__":"cc.Node","_name":"Bip001 Spine","_parent":{"__id__":7},"_children":[{"__id__":9},{"__id__":12},{"__id__":21}],"_prefab":{"__type__":"cc.PrefabInfo","root":{"__id__":1},"asset":{"__id__":0},"fileId":"b3i9fo7uVCSK9AKFYL0laI","_synced":{"default":false,"serializable":false}},"_lpos":{"__type__":"cc.Vec3","x":0.0000752642154111527,"y":-0.00000844085843709763,"z":1.16084350465506e-10},"_lrot":{"__type__":"cc.Quat","x":-0.000001973954594570372,"y":-5.031095679455076e-7,"z":-0.11632126727487835,"w":0.9932116404751893},"_euler":{"__type__":"cc.Vec3","x":-0.0002378044761224724,"y":-0.0000858969270002866,"z":-13.359679169564101}},{"__type__":"cc.Node","_name":"Bip001 L Thigh","_parent":{"__id__":8},"_children":[{"__id__":10}],"_prefab":{"__type__":"cc.PrefabInfo","root":{"__id__":1},"asset":{"__id__":0},"fileId":"10RjelhXlKsoh/tfcnnKUD","_synced":{"default":false,"serializable":false}},"_lpos":{"__type__":"cc.Vec3","x":-0.0000751780025893822,"y":-0.00000917962734092725,"z":0.000471073115477338},"_lrot":{"__type__":"cc.Quat","x":-0.012494694695705839,"y":0.9999219382543043,"z":0.0000014679518770483459,"w":2.47993858052997e-7},"_lscale":{"__type__":"cc.Vec3","x":0.999999940395355,"y":1.0000479221344,"z":1},"_euler":{"__type__":"cc.Vec3","x":-0.00016860948303415075,"y":179.99996947289017,"z":-1.4318238017754288}},{"__type__":"cc.Node","_name":"Bip001 L Calf","_parent":{"__id__":9},"_children":[{"__id__":11}],"_prefab":{"__type__":"cc.PrefabInfo","root":{"__id__":1},"asset":{"__id__":0},"fileId":"e795vRIahH9KCerBYPgIUN","_synced":{"default":false,"serializable":false}},"_lpos":{"__type__":"cc.Vec3","x":0.000384572631446645,"z":4.76837146157205e-11},"_lrot":{"__type__":"cc.Quat","x":6.8994974337126e-14,"y":3.1944729747324515e-14,"z":-0.21748200212199667,"w":0.976064331257427},"_euler":{"__type__":"cc.Vec3","x":9.402567522119873e-12,"y":5.845399131492843e-12,"z":-25.122363554928615}},{"__type__":"cc.Node","_name":"Bip001 L Foot","_parent":{"__id__":10},"_children":[{"__type__":"cc.Node","_name":"Bip001 L Toe0","_parent":{"__id__":11},"_prefab":{"__type__":"cc.PrefabInfo","root":{"__id__":1},"asset":{"__id__":0},"fileId":"f5ET5EdXRAuojzqNHYvX2w","_synced":{"default":false,"serializable":false}},"_lpos":{"__type__":"cc.Vec3","x":0.0000759027097956277,"y":0.000236152438446879,"z":-4.76837146157205e-11},"_lrot":{"__type__":"cc.Quat","x":1.5454311872698787e-8,"y":1.5454311872698787e-8,"z":0.7071067811865472,"w":0.7071067811865472},"_euler":{"__type__":"cc.Vec3","y":0.0000025044784441148167,"z":90}}],"_prefab":{"__type__":"cc.PrefabInfo","root":{"__id__":1},"asset":{"__id__":0},"fileId":"9fJjwY1AdBKo9cjTZDB111","_synced":{"default":false,"serializable":false}},"_lpos":{"__type__":"cc.Vec3","x":0.000317769270623103,"y":5.96046432696506e-12},"_lrot":{"__type__":"cc.Quat","x":-1.6105263139803266e-8,"y":1.1312266136078868e-7,"z":0.16187921406370193,"w":0.9868105796221001},"_euler":{"__type__":"cc.Vec3","x":-0.000004136397801312092,"y":0.000013814706928733356,"z":18.631978768172335}},{"__type__":"cc.Node","_name":"Bip001 Neck","_parent":{"__id__":8},"_children":[{"__type__":"cc.Node","_name":"Bip001 Head","_parent":{"__id__":12},"_prefab":{"__type__":"cc.PrefabInfo","root":{"__id__":1},"asset":{"__id__":0},"fileId":"582yW9t95LWrht4IOpUWF3","_synced":{"default":false,"serializable":false}},"_lpos":{"__type__":"cc.Vec3","x":0.0000495017957291566,"y":2.38418573078603e-11,"z":9.0949467879716e-17},"_lrot":{"__type__":"cc.Quat","x":-6.477302221649392e-9,"y":-2.9695061567959574e-7,"z":0.06907860159314716,"w":0.9976112202666162},"_euler":{"__type__":"cc.Vec3","x":0.000001625652653566807,"y":-0.000034222080829607885,"z":7.922133734554831}},{"__id__":13},{"__id__":16}],"_prefab":{"__type__":"cc.PrefabInfo","root":{"__id__":1},"asset":{"__id__":0},"fileId":"2bUH0VHWxKS4azQkYWHC3F","_synced":{"default":false,"serializable":false}},"_lpos":{"__type__":"cc.Vec3","x":0.00154076458420604,"y":1.56387489624876e-8,"z":4.34283719283422e-14}},{"__type__":"cc.Node","_name":"Bip001 L Clavicle","_parent":{"__id__":12},"_children":[{"__id__":14}],"_prefab":{"__type__":"cc.PrefabInfo","root":{"__id__":1},"asset":{"__id__":0},"fileId":"f2wBfY6GhGBKxFI4d5BaKu","_synced":{"default":false,"serializable":false}},"_lpos":{"__type__":"cc.Vec3","x":-0.000330190057866275,"y":3.00252423812708e-7,"z":0.000612043484579772},"_lrot":{"__type__":"cc.Quat","x":0.6109167505727511,"y":-0.04922639714201474,"z":0.7892677405365912,"w":-0.03760212018373044},"_euler":{"__type__":"cc.Vec3","x":178.16671852674128,"y":-104.62806675095268,"z":-6.863405288526942}},{"__type__":"cc.Node","_name":"Bip001 L UpperArm","_parent":{"__id__":13},"_children":[{"__id__":15}],"_prefab":{"__type__":"cc.PrefabInfo","root":{"__id__":1},"asset":{"__id__":0},"fileId":"b75C8wIahMM6DWjA5zMsPs","_synced":{"default":false,"serializable":false}},"_lpos":{"__type__":"cc.Vec3","x":0.000302730302792042,"z":-1.90734858462882e-10},"_lrot":{"__type__":"cc.Quat","x":0.07117785441541753,"y":0.4558953894842389,"z":0.09732290259096675,"w":0.8818284184120518},"_euler":{"__type__":"cc.Vec3","x":2.17030429636925,"y":54.416501053245895,"z":13.682625110721464}},{"__type__":"cc.Node","_name":"Bip001 L Forearm","_parent":{"__id__":14},"_children":[{"__type__":"cc.Node","_name":"Bip001 L Hand","_parent":{"__id__":15},"_prefab":{"__type__":"cc.PrefabInfo","root":{"__id__":1},"asset":{"__id__":0},"fileId":"33+c1Zk09ChZ5U1ACHwYMq","_synced":{"default":false,"serializable":false}},"_lpos":{"__type__":"cc.Vec3","x":0.000569271680433303,"y":-2.38418573078603e-11,"z":9.5367429231441e-11},"_lrot":{"__type__":"cc.Quat","x":-0.6933142898874123,"y":0.033082472877855436,"z":0.14403970040933603,"w":0.7053179496738957},"_euler":{"__type__":"cc.Vec3","x":-90.16618055623981,"y":14.448137845297664,"z":9.05105267499611}}],"_prefab":{"__type__":"cc.PrefabInfo","root":{"__id__":1},"asset":{"__id__":0},"fileId":"73vgIawg9LSJQOLMgdCxzV","_synced":{"default":false,"serializable":false}},"_lpos":{"__type__":"cc.Vec3","x":0.000510638579726219,"z":-1.90734858462882e-10},"_lrot":{"__type__":"cc.Quat","x":-2.7998892764835967e-8,"y":2.065408515985999e-8,"z":-0.20076294724562121,"w":0.979639851686961},"_euler":{"__type__":"cc.Vec3","x":-0.000002901874553795768,"y":0.0000018212763881522312,"z":-23.163155296263078}},{"__type__":"cc.Node","_name":"Bip001 R Clavicle","_parent":{"__id__":12},"_children":[{"__id__":17}],"_prefab":{"__type__":"cc.PrefabInfo","root":{"__id__":1},"asset":{"__id__":0},"fileId":"9dPEwvsH5Eb6d4VtLXad3Z","_synced":{"default":false,"serializable":false}},"_lpos":{"__type__":"cc.Vec3","x":-0.000330190057866275,"y":3.03626052300388e-7,"z":-0.000612043484579772},"_lrot":{"__type__":"cc.Quat","x":0.7459261383458777,"y":-0.00029603452869143376,"z":-0.666028556178334,"w":-0.00026617845166469187},"_euler":{"__type__":"cc.Vec3","x":-179.95465417695337,"y":83.52257383452239,"z":-0.004989023470625068}},{"__type__":"cc.Node","_name":"Bip001 R UpperArm","_parent":{"__id__":16},"_children":[{"__id__":18}],"_prefab":{"__type__":"cc.PrefabInfo","root":{"__id__":1},"asset":{"__id__":0},"fileId":"7ahQKEfAdNS5Og7mbptqas","_synced":{"default":false,"serializable":false}},"_lpos":{"__type__":"cc.Vec3","x":0.000302730360999703,"y":-2.38418573078603e-11},"_lrot":{"__type__":"cc.Quat","x":0.2242444995440684,"y":-0.26957281748018325,"z":-0.11677553211890349,"w":0.9291977053342163},"_euler":{"__type__":"cc.Vec3","x":22.079141831841312,"y":-28.466046309026574,"z":-19.74992926470223}},{"__type__":"cc.Node","_name":"Bip001 R Forearm","_parent":{"__id__":17},"_children":[{"__id__":19}],"_prefab":{"__type__":"cc.PrefabInfo","root":{"__id__":1},"asset":{"__id__":0},"fileId":"8cN4QA2flEKaiacMMTjuWV","_synced":{"default":false,"serializable":false}},"_lpos":{"__type__":"cc.Vec3","x":0.000510638521518558},"_lrot":{"__type__":"cc.Quat","x":1.7089117733069137e-8,"y":3.861246268845457e-8,"z":-0.5097075121584418,"w":0.8603477506504277},"_euler":{"__type__":"cc.Vec3","x":0.00000820171587557094,"y":0.000010001930597449375,"z":-61.2886984781879}},{"__type__":"cc.Node","_name":"Bip001 R Hand","_parent":{"__id__":18},"_children":[{"__id__":20}],"_prefab":{"__type__":"cc.PrefabInfo","root":{"__id__":1},"asset":{"__id__":0},"fileId":"d19AF67oZNkIqNdcBgg2rC","_synced":{"default":false,"serializable":false}},"_lpos":{"__type__":"cc.Vec3","x":0.000569271855056286,"y":-2.25514043605179e-19},"_lrot":{"__type__":"cc.Quat","x":0.9219166656020916,"y":0.02302982104238916,"z":0.26511505302393545,"w":0.2815196222077467},"_euler":{"__type__":"cc.Vec3","x":148.90586030737632,"y":-29.003090619889562,"z":11.053956710178031}},{"__type__":"cc.Node","_name":"Bone001","_parent":{"__id__":19},"_children":[{"__type__":"cc.Node","_name":"Bone002","_parent":{"__id__":20},"_prefab":{"__type__":"cc.PrefabInfo","root":{"__id__":1},"asset":{"__id__":0},"fileId":"93ZZ6Tg7NA5brlBSga0b3+","_synced":{"default":false,"serializable":false}},"_lpos":{"__type__":"cc.Vec3","x":0.00622813683003187,"y":-1.63912772244146e-9,"z":5.9604643443123e-10}}],"_prefab":{"__type__":"cc.PrefabInfo","root":{"__id__":1},"asset":{"__id__":0},"fileId":"9d44D6aAJJJbJ4kJXD1Ayp","_synced":{"default":false,"serializable":false}},"_lpos":{"__type__":"cc.Vec3","x":-0.000154506153194234,"y":0.000211154067073949,"z":0.00202487828209996},"_lrot":{"__type__":"cc.Quat","x":0.637290188637987,"y":0.07970428578213569,"z":0.7642259108561157,"w":-0.0588829302078186},"_euler":{"__type__":"cc.Vec3","x":-168.64493947466457,"y":-100.41637120996559,"z":0.6640613033163799}},{"__type__":"cc.Node","_name":"Bip001 R Thigh","_parent":{"__id__":8},"_children":[{"__id__":22}],"_prefab":{"__type__":"cc.PrefabInfo","root":{"__id__":1},"asset":{"__id__":0},"fileId":"e1zA0vEqtCL6xi/caPbLfB","_synced":{"default":false,"serializable":false}},"_lpos":{"__type__":"cc.Vec3","x":-0.0000751778061385266,"y":-0.00000917701709113317,"z":-0.00047107323189266},"_lrot":{"__type__":"cc.Quat","x":-0.012495892189558162,"y":0.9999219232903117,"z":0.0000013331405242563569,"w":1.1650836802446062e-7},"_euler":{"__type__":"cc.Vec3","x":-0.0001529693261606246,"y":179.99998473644456,"z":-1.4319610352008258}},{"__type__":"cc.Node","_name":"Bip001 R Calf","_parent":{"__id__":21},"_children":[{"__id__":23}],"_prefab":{"__type__":"cc.PrefabInfo","root":{"__id__":1},"asset":{"__id__":0},"fileId":"7brmX7liRPaL35iEKIaZZf","_synced":{"default":false,"serializable":false}},"_lpos":{"__type__":"cc.Vec3","x":0.000384572660550475,"y":1.73472343720272e-20,"z":4.76837146157205e-11},"_lrot":{"__type__":"cc.Quat","x":1.6786358243942812e-14,"y":1.808826312292143e-14,"z":-0.2183951871852553,"w":0.9758604112342695},"_euler":{"__type__":"cc.Vec3","x":2.5755070873923103e-12,"y":2.7004278413610287e-12,"z":-25.22958417687751}},{"__type__":"cc.Node","_name":"Bip001 R Foot","_parent":{"__id__":22},"_children":[{"__type__":"cc.Node","_name":"Bip001 R Toe0","_parent":{"__id__":23},"_prefab":{"__type__":"cc.PrefabInfo","root":{"__id__":1},"asset":{"__id__":0},"fileId":"f51LHcMqBIe7X2a3juref7","_synced":{"default":false,"serializable":false}},"_lpos":{"__type__":"cc.Vec3","x":0.0000759027170715854,"y":0.000236152438446879,"z":-4.76837146157205e-11},"_lrot":{"__type__":"cc.Quat","x":-6.495474136478361e-8,"y":5.470479984923051e-7,"z":0.70710660237248,"w":0.7071069600003551},"_euler":{"__type__":"cc.Vec3","y":-0.000010526363761329827,"z":90}}],"_prefab":{"__type__":"cc.PrefabInfo","root":{"__id__":1},"asset":{"__id__":0},"fileId":"de/wX1TuhCgrI8cA4oeQ10","_synced":{"default":false,"serializable":false}},"_lpos":{"__type__":"cc.Vec3","x":0.000317769299726933,"y":8.67361718601358e-21},"_lrot":{"__type__":"cc.Quat","x":1.7205175730171035e-8,"y":-1.3369759350412249e-8,"z":0.16279490083495826,"w":0.986659931416157},"_euler":{"__type__":"cc.Vec3","x":0.0000023175173952036635,"y":-0.0000019351567054753774,"z":18.738319315528916}},{"__type__":"cc.Node","_name":"QiangBing","_parent":{"__id__":5},"_components":[{"__type__":"cc.SkinningModelComponent","node":{"__id__":24},"_materials":[{"__uuid__":"1bAm45eDJO/a5l8jbTlDWz"}],"lightmapSettings":{"__type__":"cc.ModelLightmapSettings"},"_mesh":{"__uuid__":"80fxZcrrhHt6l8Q44DX8T4@34d70"},"_skeleton":{"__uuid__":"80fxZcrrhHt6l8Q44DX8T4@438fe"},"_skinningRoot":{"__id__":2}}],"_prefab":{"__type__":"cc.PrefabInfo","root":{"__id__":1},"asset":{"__id__":0},"fileId":"c20hE/9fJFZor3e7zcDend","_synced":{"default":false,"serializable":false}},"_lscale":{"__type__":"cc.Vec3","x":6.25,"y":6.25,"z":6.25},"_euler":{"__type__":"cc.Vec3","x":0.000007629393657927899}},{"__type__":"cc.Node","_name":"rank","_parent":{"__id__":1},"_children":[{"__id__":26},{"__id__":27},{"__id__":28},{"__id__":29},{"__id__":30},{"__id__":31},{"__id__":32}],"_prefab":{"__type__":"cc.PrefabInfo","root":{"__id__":1},"asset":{"__id__":0},"fileId":"56RqON+ZtMUr8Yk/zqPyvn","_synced":{"default":false,"serializable":false}}},{"__type__":"cc.Node","_name":"rank1","_parent":{"__id__":25},"_components":[{"__type__":"cc.ModelComponent","node":{"__id__":26},"_materials":[{"__uuid__":"b7/9TPxzdKC4ZSnFuDs+yS"}],"lightmapSettings":{"__type__":"cc.ModelLightmapSettings"},"_mesh":{"__uuid__":"cbljn3jq9ORaQVxcW8rtGq@b8a2d"}}],"_prefab":{"__type__":"cc.PrefabInfo","root":{"__id__":1},"asset":{"__id__":0},"fileId":"93/u6Vb2tGwqrdQK5Jadej","_synced":{"default":false,"serializable":false}},"_lpos":{"__type__":"cc.Vec3","y":0.01},"_lrot":{"__type__":"cc.Quat","x":-0.7071067811865476,"w":0.7071067811865475},"_euler":{"__type__":"cc.Vec3","x":-90.00000000000003}},{"__type__":"cc.Node","_name":"rank5","_parent":{"__id__":25},"_components":[{"__type__":"cc.ModelComponent","node":{"__id__":27},"_materials":[{"__uuid__":"28VpQUlwJPwo/zE9fcC+Kj"}],"lightmapSettings":{"__type__":"cc.ModelLightmapSettings"},"_mesh":{"__uuid__":"cbljn3jq9ORaQVxcW8rtGq@b8a2d"}}],"_prefab":{"__type__":"cc.PrefabInfo","root":{"__id__":1},"asset":{"__id__":0},"fileId":"10D47DAn5NTo5/cH+Aw5Sr","_synced":{"default":false,"serializable":false}},"_lpos":{"__type__":"cc.Vec3","y":0.01},"_lrot":{"__type__":"cc.Quat","x":-0.7071067811865476,"w":0.7071067811865475},"_euler":{"__type__":"cc.Vec3","x":-90.00000000000003}},{"__type__":"cc.Node","_name":"rank6","_parent":{"__id__":25},"_components":[{"__type__":"cc.ModelComponent","node":{"__id__":28},"_materials":[{"__uuid__":"25utRMcbFHe4slwH1VwAcI"}],"lightmapSettings":{"__type__":"cc.ModelLightmapSettings"},"_mesh":{"__uuid__":"cbljn3jq9ORaQVxcW8rtGq@b8a2d"}}],"_prefab":{"__type__":"cc.PrefabInfo","root":{"__id__":1},"asset":{"__id__":0},"fileId":"ccpSYKyGZApJN0v+Y1hLt3","_synced":{"default":false,"serializable":false}},"_lpos":{"__type__":"cc.Vec3","y":0.01},"_lrot":{"__type__":"cc.Quat","x":-0.7071067811865476,"w":0.7071067811865475},"_euler":{"__type__":"cc.Vec3","x":-90.00000000000003}},{"__type__":"cc.Node","_name":"rank7","_parent":{"__id__":25},"_components":[{"__type__":"cc.ModelComponent","node":{"__id__":29},"_materials":[{"__uuid__":"53/JjQ0gVBRaDNvjSdPMTb"}],"lightmapSettings":{"__type__":"cc.ModelLightmapSettings"},"_mesh":{"__uuid__":"cbljn3jq9ORaQVxcW8rtGq@b8a2d"}}],"_prefab":{"__type__":"cc.PrefabInfo","root":{"__id__":1},"asset":{"__id__":0},"fileId":"6aKeSOsixEJYyFLe9WNyE3","_synced":{"default":false,"serializable":false}},"_lpos":{"__type__":"cc.Vec3","y":0.01},"_lrot":{"__type__":"cc.Quat","x":-0.7071067811865476,"w":0.7071067811865475},"_euler":{"__type__":"cc.Vec3","x":-90.00000000000003}},{"__type__":"cc.Node","_name":"rank8","_parent":{"__id__":25},"_components":[{"__type__":"cc.ModelComponent","node":{"__id__":30},"_materials":[{"__uuid__":"55+SxRJbxBzrjuwhSMNX71"}],"lightmapSettings":{"__type__":"cc.ModelLightmapSettings"},"_mesh":{"__uuid__":"cbljn3jq9ORaQVxcW8rtGq@b8a2d"}}],"_prefab":{"__type__":"cc.PrefabInfo","root":{"__id__":1},"asset":{"__id__":0},"fileId":"deRC7rYR5Gi5iZOEYykIUg","_synced":{"default":false,"serializable":false}},"_lpos":{"__type__":"cc.Vec3","y":0.01},"_lrot":{"__type__":"cc.Quat","x":-0.7071067811865476,"w":0.7071067811865475},"_euler":{"__type__":"cc.Vec3","x":-90.00000000000003}},{"__type__":"cc.Node","_name":"rank9","_parent":{"__id__":25},"_components":[{"__type__":"cc.ModelComponent","node":{"__id__":31},"_materials":[{"__uuid__":"b0eF7GruxCvqPJl1ckhhaH"}],"lightmapSettings":{"__type__":"cc.ModelLightmapSettings"},"_mesh":{"__uuid__":"cbljn3jq9ORaQVxcW8rtGq@b8a2d"}}],"_prefab":{"__type__":"cc.PrefabInfo","root":{"__id__":1},"asset":{"__id__":0},"fileId":"81s4oWen5KYKrnNHHnpJKn","_synced":{"default":false,"serializable":false}},"_lpos":{"__type__":"cc.Vec3","y":0.01},"_lrot":{"__type__":"cc.Quat","x":-0.7071067811865476,"w":0.7071067811865475},"_euler":{"__type__":"cc.Vec3","x":-90.00000000000003}},{"__type__":"cc.Node","_name":"rank10","_parent":{"__id__":25},"_components":[{"__type__":"cc.ModelComponent","node":{"__id__":32},"_materials":[{"__uuid__":"37YXnhAxBETYNqTsLUH6Nj"}],"lightmapSettings":{"__type__":"cc.ModelLightmapSettings"},"_mesh":{"__uuid__":"cbljn3jq9ORaQVxcW8rtGq@b8a2d"}}],"_prefab":{"__type__":"cc.PrefabInfo","root":{"__id__":1},"asset":{"__id__":0},"fileId":"deqJAMKUBPs7z0aVGvnBVB","_synced":{"default":false,"serializable":false}},"_lpos":{"__type__":"cc.Vec3","y":0.01},"_lrot":{"__type__":"cc.Quat","x":-0.7071067811865476,"w":0.7071067811865475},"_euler":{"__type__":"cc.Vec3","x":-90.00000000000003}}]
