[{"__type__":"cc.SpriteFrame","content":{"name":"toutu","rect":{"x":3,"y":3,"width":750,"height":325},"offset":{"x":0,"y":23},"originalSize":{"width":750,"height":371},"rotated":true,"capInsets":[0,0,0,0],"texture":"166f2e027@6c48a"}},{"__type__":"cc.SpriteFrame","content":{"name":"2","rect":{"x":199,"y":794,"width":167,"height":167},"offset":{"x":0,"y":0},"originalSize":{"width":167,"height":167},"rotated":false,"capInsets":[47,58,34,57],"texture":"166f2e027@6c48a"}},{"__type__":"cc.SpriteFrame","content":{"name":"nniu","rect":{"x":334,"y":109,"width":204,"height":91},"offset":{"x":-0.5,"y":0.5},"originalSize":{"width":221,"height":108},"rotated":false,"capInsets":[0,0,0,0],"texture":"166f2e027@6c48a"}},{"__type__":"cc.SpriteFrame","content":{"name":"anniu1","rect":{"x":334,"y":3,"width":222,"height":100},"offset":{"x":-0.5,"y":1},"originalSize":{"width":227,"height":102},"rotated":false,"capInsets":[0,0,0,0],"texture":"166f2e027@6c48a"}},{"__type__":"cc.ImageAsset","content":{"fmt":"0","w":559,"h":1011}},{"__type__":"cc.SpriteFrame","content":{"name":"qu","rect":{"x":334,"y":206,"width":203,"height":90},"offset":{"x":-0.5,"y":1.5},"originalSize":{"width":212,"height":101},"rotated":false,"capInsets":[0,0,0,0],"texture":"166f2e027@6c48a"}},{"__type__":"cc.SpriteFrame","content":{"name":"4","rect":{"x":334,"y":434,"width":174,"height":174},"offset":{"x":0,"y":0},"originalSize":{"width":174,"height":174},"rotated":false,"capInsets":[58,57,48,49],"texture":"166f2e027@6c48a"}},{"__type__":"cc.SpriteFrame","content":{"name":"ka1","rect":{"x":3,"y":759,"width":249,"height":190},"offset":{"x":-2.5,"y":7.5},"originalSize":{"width":266,"height":207},"rotated":true,"capInsets":[0,0,0,0],"texture":"166f2e027@6c48a"}},{"__type__":"cc.SpriteFrame","content":{"name":"ka","rect":{"x":334,"y":302,"width":126,"height":175},"offset":{"x":-0.5,"y":5.5},"originalSize":{"width":159,"height":204},"rotated":true,"capInsets":[0,0,0,0],"texture":"166f2e027@6c48a"}},{"__type__":"cc.SpriteFrame","content":{"name":"1","rect":{"x":372,"y":794,"width":167,"height":167},"offset":{"x":0,"y":0},"originalSize":{"width":167,"height":167},"rotated":false,"capInsets":[53,37,62,48],"texture":"166f2e027@6c48a"}},{"__type__":"cc.SpriteFrame","content":{"name":"3","rect":{"x":334,"y":614,"width":174,"height":174},"offset":{"x":0,"y":0},"originalSize":{"width":174,"height":174},"rotated":false,"capInsets":[40,36,69,76],"texture":"166f2e027@6c48a"}}]
